sparray/__init__.py
sparray/_merge.cpython-35m-darwin.so
sparray/_merge.pyx
sparray/base.py
sparray/compat.py
sparray-0.0.3.dist-info/DESCRIPTION.rst
sparray-0.0.3.dist-info/METADATA
sparray-0.0.3.dist-info/RECORD
sparray-0.0.3.dist-info/WHEEL
sparray-0.0.3.dist-info/metadata.json
sparray-0.0.3.dist-info/top_level.txt
