Metadata-Version: 1.0
Name: sparray
Version: 0.0.3
Summary: Sparse representation for ndarrays
Home-page: http://github.com/perimosocordiae/sparray
Author: CJ Carey
Author-email: perimosocordiae@gmail.com
License: MIT
Platform: UNKNOWN
